{
  "PT": {
    "external": {
      "name": "Griseofulvina",
      "suspension": "Suspender 1 dia antes da cirurgia se uso profilático",
      "risk": "Interações com anestésicos, risco hepático e hematológico; indutor enzimático (CYP)",
      "reintroduction": "Reintroduzir após cirurgia com função hepática e hematológica estáveis"
    },
    "bulario": {
      "nomePrincipioAtivo": "Griseofulvina",
      "nomeComercial": "Fulcin, Grisovin",
      "mecanismoAcao": "Liga-se à queratina da pele, cabelo e unhas, inibindo o crescimento de fungos dermatófitos",
      "farmacocinetica": "Oral, melhor absorção com alimentos gordurosos, metabolização hepática, excreção renal",
      "farmacodinamica": "Fungistático contra Trichophyton, Microsporum e Epidermophyton",
      "indicacoes": "Tineas (corporis, capitis, unguium, pedis), onicomicose, dermatofitoses crônicas",
      "reacoesAdversas": "Cefaleia, tontura, náuseas, rash, hepatotoxicidade, leucopenia",
      "riscoGravidez": "Categoria X",
      "riscoLactacao": "Contraindicado",
      "administracao": "Oral",
      "doseMaxima": "1 g/dia",
      "doseMinima": "250 mg/dia",
      "classificacao": "Antifúngico oral (benzofurano)",
      "apresentacao": "Comprimidos de 250 mg; suspensão 125 mg/5 mL",
      "interacaoMedicamento": "Indutor enzimático: reduz eficácia de anticoagulantes, anticoncepcionais, ciclosporina",
      "posologia": "500–1000 mg/dia por 4–8 semanas (pele); até 12 meses (unhas)",
      "armazenamento": "Temperatura ambiente",
      "preparo": "Uso oral com alimentos gordurosos",
      "solucoesCompatíveis": "Não aplicável",
      "contraindicacoes": "Doença hepática ativa, porfiria, gravidez, alergia a griseofulvina",
      "cuidadosMedicos": "Monitorar função hepática, hemograma e sinais de hipersensibilidade",
      "cuidadosFarmaceuticos": "Orientar ingestão com alimentos gordurosos e evitar gravidez durante tratamento",
      "cuidadosEnfermagem": "Observar efeitos colaterais gastrointestinais e cutâneos",
      "fontesBibliograficas": "ANVISA, BNF, UpToDate, Micromedex, FDA"
    }
  },
  "US": {
    "external": {
      "name": "Griseofulvin",
      "suspension": "Hold 1 day prior to surgery if used prophylactically",
      "risk": "CYP inducer, hepatic and hematologic risks; interacts with anesthetics",
      "reintroduction": "Restart after surgery when liver and hematologic profiles are stable"
    },
    "bulario": {
      "nomePrincipioAtivo": "Griseofulvin",
      "nomeComercial": "Gris-PEG, Fulvicin, Grifulvin V",
      "mecanismoAcao": "Binds to keratin in skin, hair, nails inhibiting dermatophyte growth",
      "farmacocinetica": "Oral, best absorbed with fatty meals, hepatic metabolism, renal excretion",
      "farmacodinamica": "Fungistatic against Trichophyton, Microsporum, Epidermophyton",
      "indicacoes": "Tinea infections (capitis, corporis, pedis, unguium), chronic dermatophytoses",
      "reacoesAdversas": "Headache, dizziness, nausea, rash, hepatotoxicity, leukopenia",
      "riscoGravidez": "Category X",
      "riscoLactacao": "Contraindicated",
      "administracao": "Oral",
      "doseMaxima": "1 g/day",
      "doseMinima": "250 mg/day",
      "classificacao": "Oral antifungal (benzofuran derivative)",
      "apresentacao": "Tablets 250 mg; suspension 125 mg/5 mL",
      "interacaoMedicamento": "CYP inducer: decreases efficacy of anticoagulants, contraceptives, cyclosporine",
      "posologia": "500–1000 mg/day for 4–8 weeks (skin); up to 12 months (nails)",
      "armazenamento": "Store at room temperature",
      "preparo": "Take orally with fatty food",
      "solucoesCompatíveis": "Not applicable",
      "contraindicacoes": "Active liver disease, porphyria, pregnancy, hypersensitivity",
      "cuidadosMedicos": "Monitor liver enzymes, CBC, and hypersensitivity signs",
      "cuidadosFarmaceuticos": "Advise fatty meal intake, strict contraception during treatment",
      "cuidadosEnfermagem": "Monitor for GI and skin side effects",
      "fontesBibliograficas": "FDA, Micromedex, UpToDate, BNF"
    }
  },
  "ES": {
    "external": {
      "name": "Griseofulvina",
      "suspension": "Suspender 1 día antes de la cirugía si es profiláctico",
      "risk": "Riesgo hepático y hematológico; inductor enzimático; interacciones anestésicas",
      "reintroduction": "Reintroducir tras la cirugía si función hepática y hematológica están estables"
    },
    "bulario": {
      "nomePrincipioAtivo": "Griseofulvina",
      "nomeComercial": "Fulcin, Grisovin",
      "mecanismoAcao": "Se une a la queratina y previene la invasión fúngica en piel, pelo y uñas",
      "farmacocinetica": "Oral, mejor absorción con comidas grasas, metabolismo hepático, excreción renal",
      "farmacodinamica": "Fungistático contra Trichophyton, Microsporum y Epidermophyton",
      "indicacoes": "Tiñas (capitis, corporis, pedis, unguium), onicomicosis, dermatofitosis crónica",
      "reacoesAdversas": "Cefalea, náuseas, exantema, hepatotoxicidad, leucopenia",
      "riscoGravidez": "Categoría X",
      "riscoLactacao": "Contraindicado",
      "administracao": "Oral",
      "doseMaxima": "1 g/día",
      "doseMinima": "250 mg/día",
      "classificacao": "Antifúngico oral (derivado bencofurano)",
      "apresentacao": "Tabletas de 250 mg; suspensión 125 mg/5 mL",
      "interacaoMedicamento": "Reduce eficacia de anticonceptivos, anticoagulantes, ciclosporina",
      "posologia": "500–1000 mg/día durante 4–8 semanas (piel); hasta 12 meses (uñas)",
      "armazenamento": "Temperatura ambiente",
      "preparo": "Administrar con comida grasa",
      "solucoesCompatíveis": "No aplica",
      "contraindicacoes": "Enfermedad hepática activa, porfiria, embarazo",
      "cuidadosMedicos": "Controlar enzimas hepáticas, hemograma, signos de alergia",
      "cuidadosFarmaceuticos": "Aconsejar sobre anticoncepción y comidas grasas",
      "cuidadosEnfermagem": "Observar efectos gastrointestinales y cutáneos",
      "fontesBibliograficas": "AEMPS, BNF, UpToDate, Micromedex"
    }
  },
  "CH": {
    "external": {
      "name": "灰黄霉素",
      "suspension": "如为预防性使用，建议术前1天停药",
      "risk": "有肝毒性和血液系统风险，具酶诱导作用，影响麻醉药代谢",
      "reintroduction": "术后肝功能和血象稳定后可重新使用"
    },
    "bulario": {
      "nomePrincipioAtivo": "灰黄霉素",
      "nomeComercial": "Grisovin, Fulvicin",
      "mecanismoAcao": "与角蛋白结合抑制真菌生长",
      "farmacocinetica": "口服吸收佳，脂肪餐促进吸收，经肝代谢，肾脏排泄",
      "farmacodinamica": "对毛癣菌、小孢子菌、表皮癣菌具抑菌作用",
      "indicacoes": "头癣、体癣、足癣、甲癣、慢性皮肤癣",
      "reacoesAdversas": "头痛、恶心、皮疹、肝损害、白细胞减少",
      "riscoGravidez": "X类",
      "riscoLactacao": "禁用于哺乳期",
      "administracao": "口服",
      "doseMaxima": "每日1克",
      "doseMinima": "每日250毫克",
      "classificacao": "口服抗真菌药（苯并呋喃类）",
      "apresentacao": "片剂250毫克；口服液125毫克/5毫升",
      "interacaoMedicamento": "降低避孕药、抗凝药、环孢素等药效",
      "posologia": "每日500–1000毫克，皮肤感染疗程4–8周，甲癣最长可达12个月",
      "armazenamento": "室温保存",
      "preparo": "建议随高脂餐服用",
      "solucoesCompatíveis": "不适用",
      "contraindicacoes": "活动性肝病、卟啉病、妊娠期",
      "cuidadosMedicos": "监测肝酶、血常规、过敏反应",
      "cuidadosFarmaceuticos": "强调避孕措施与饮食要求",
      "cuidadosEnfermagem": "观察胃肠与皮肤不良反应",
      "fontesBibliograficas": "中国药典、UpToDate、Micromedex、BNF"
    }
  }
}