{
  "PT": {
    "external": {
      "name": "Nistatina",
      "suspension": "Manter até o dia da cirurgia se uso tópico ou oral local",
      "risk": "Baixo risco sistêmico; uso oral ou tópico sem interações anestésicas relevantes",
      "reintroduction": "Reintroduzir conforme tolerância gastrointestinal e/ou manutenção de lesões mucocutâneas"
    },
    "bulario": {
      "nomePrincipioAtivo": "Nistatina",
      "nomeComercial": "Micostatin, Nilstat, Canditrat",
      "mecanismoAcao": "Liga-se ao ergosterol da membrana fúngica, causando poros e morte celular",
      "farmacocinetica": "Não absorvida por via oral ou tópica; ação local",
      "farmacodinamica": "Fungicida contra Candida spp.",
      "indicacoes": "Candidíase oral, esofágica, cutânea, vaginal; prevenção em imunossuprimidos",
      "reacoesAdversas": "Náuseas, diarreia, irritação local, sabor amargo",
      "riscoGravidez": "Categoria A",
      "riscoLactacao": "Compatível",
      "administracao": "Oral (suspensão), tópica ou vaginal",
      "doseMaxima": "6.000.000 UI/dia (oral); conforme necessidade tópica",
      "doseMinima": "500.000 UI/dose",
      "classificacao": "Antifúngico poliênico tópico",
      "apresentacao": "Suspensão oral, comprimidos vaginais, creme ou pomada dermatológica",
      "interacaoMedicamento": "Sem interações sistêmicas relevantes",
      "posologia": "100.000–500.000 UI 4x/dia por 7 a 14 dias (oral); 1x/dia intravaginal por 14 dias",
      "armazenamento": "Temperatura ambiente, protegido da luz",
      "preparo": "Agitar bem a suspensão antes do uso",
      "solucoesCompatíveis": "Não aplicável",
      "contraindicacoes": "Hipersensibilidade à nistatina ou componentes da fórmula",
      "cuidadosMedicos": "Avaliar eficácia clínica e necessidade de extensão de tratamento",
      "cuidadosFarmaceuticos": "Orientar agitação e manter dose mesmo com melhora clínica precoce",
      "cuidadosEnfermagem": "Observar tolerância oral, irritação local e aderência terapêutica",
      "fontesBibliograficas": "ANVISA, BNF, FDA, Micromedex, UpToDate"
    }
  },
  "US": {
    "external": {
      "name": "Nystatin",
      "suspension": "Continue up to day of surgery for topical or oral local treatment",
      "risk": "Minimal systemic absorption; safe with anesthetics when used locally",
      "reintroduction": "Restart as needed for mucosal or cutaneous candidiasis"
    },
    "bulario": {
      "nomePrincipioAtivo": "Nystatin",
      "nomeComercial": "Mycostatin, Nilstat, Bio-Statin",
      "mecanismoAcao": "Binds to ergosterol in fungal membrane, forms pores leading to cell death",
      "farmacocinetica": "Not absorbed orally or topically; acts locally",
      "farmacodinamica": "Fungicidal against Candida spp.",
      "indicacoes": "Oral, esophageal, cutaneous, vaginal candidiasis; prophylaxis in immunocompromised",
      "reacoesAdversas": "Nausea, diarrhea, local irritation, bitter taste",
      "riscoGravidez": "Category A",
      "riscoLactacao": "Compatible",
      "administracao": "Oral suspension, topical cream/ointment, vaginal tablet",
      "doseMaxima": "6,000,000 units/day (oral); topical as needed",
      "doseMinima": "500,000 units/dose",
      "classificacao": "Topical polyene antifungal",
      "apresentacao": "Oral suspension, vaginal tablets, dermatologic cream/ointment",
      "interacaoMedicamento": "No significant systemic drug interactions",
      "posologia": "100,000–500,000 units 4x/day for 7–14 days (oral); 1x/day vaginal for 14 days",
      "armazenamento": "Store at room temperature, protect from light",
      "preparo": "Shake oral suspension well before use",
      "solucoesCompatíveis": "Not applicable",
      "contraindicacoes": "Hypersensitivity to nystatin or formulation components",
      "cuidadosMedicos": "Evaluate treatment efficacy and need for prolongation",
      "cuidadosFarmaceuticos": "Ensure agitation of suspension and full adherence",
      "cuidadosEnfermagem": "Monitor oral tolerance, local irritation, and compliance",
      "fontesBibliograficas": "FDA, Micromedex, UpToDate, BNF"
    }
  },
  "ES": {
    "external": {
      "name": "Nistatina",
      "suspension": "Mantener hasta el día de la cirugía si se usa por vía oral local o tópica",
      "risk": "Mínima absorción sistémica; sin interacciones relevantes con anestesia",
      "reintroduction": "Reintroducir según la tolerancia digestiva y persistencia de lesiones"
    },
    "bulario": {
      "nomePrincipioAtivo": "Nistatina",
      "nomeComercial": "Mycostatin, Nilstat, Candistatin",
      "mecanismoAcao": "Se une al ergosterol de la membrana fúngica, provocando poros y muerte celular",
      "farmacocinetica": "No se absorbe por vía oral o tópica; acción local",
      "farmacodinamica": "Fungicida frente a Candida spp.",
      "indicacoes": "Candidiasis oral, esofágica, cutánea, vaginal; profilaxis en inmunodeprimidos",
      "reacoesAdversas": "Náuseas, diarrea, irritación local, sabor amargo",
      "riscoGravidez": "Categoría A",
      "riscoLactacao": "Compatible",
      "administracao": "Vía oral (suspensión), tópica o vaginal",
      "doseMaxima": "6.000.000 UI/día (oral); tópica según necesidad",
      "doseMinima": "500.000 UI/dosis",
      "classificacao": "Antifúngico poliénico tópico",
      "apresentacao": "Suspensión oral, comprimidos vaginales, crema/pomada dérmica",
      "interacaoMedicamento": "Sin interacciones sistémicas relevantes",
      "posologia": "100.000–500.000 UI 4x/día por 7–14 días (oral); 1/día vaginal por 14 días",
      "armazenamento": "Temperatura ambiente, protegido de la luz",
      "preparo": "Agitar bien la suspensión antes del uso",
      "solucoesCompatíveis": "No aplica",
      "contraindicacoes": "Hipersensibilidad a nistatina o excipientes",
      "cuidadosMedicos": "Evaluar efectividad clínica y duración del tratamiento",
      "cuidadosFarmaceuticos": "Instruir en agitación y cumplimiento del esquema completo",
      "cuidadosEnfermagem": "Observar tolerancia oral, irritación y adhesión al tratamiento",
      "fontesBibliograficas": "AEMPS, UpToDate, Micromedex, BNF"
    }
  },
  "CH": {
    "external": {
      "name": "制霉菌素",
      "suspension": "如为口腔或局部用药，可持续至手术日",
      "risk": "几乎无全身吸收，与麻醉药无显著相互作用",
      "reintroduction": "术后根据局部耐受情况和黏膜损伤情况重用"
    },
    "bulario": {
      "nomePrincipioAtivo": "制霉菌素",
      "nomeComercial": "Mycostatin, 妮司他丁",
      "mecanismoAcao": "与真菌细胞膜麦角固醇结合，形成孔洞导致细胞破裂死亡",
      "farmacocinetica": "口服或外用均不被吸收，仅局部作用",
      "farmacodinamica": "对念珠菌具杀菌作用",
      "indicacoes": "口腔、食管、皮肤、阴道念珠菌病；免疫抑制者的预防",
      "reacoesAdversas": "恶心、腹泻、局部刺激、苦味",
      "riscoGravidez": "A类",
      "riscoLactacao": "可用于哺乳期",
      "administracao": "口服混悬液、阴道片、皮肤霜/软膏",
      "doseMaxima": "每日600万单位（口服）；外用视情况而定",
      "doseMinima": "每次50万单位",
      "classificacao": "多烯类局部抗真菌药",
      "apresentacao": "口服混悬液、阴道片、皮肤制剂",
      "interacaoMedicamento": "无显著全身性相互作用",
      "posologia": "每次10–50万单位，每日4次，疗程7–14天",
      "armazenamento": "室温保存，避光",
      "preparo": "使用前充分摇匀混悬液",
      "solucoesCompatíveis": "不适用",
      "contraindicacoes": "对制霉菌素或辅料过敏者禁用",
      "cuidadosMedicos": "评估疗效与是否需延长疗程",
      "cuidadosFarmaceuticos": "指导规范使用，完成疗程",
      "cuidadosEnfermagem": "关注口腔耐受、局部反应与依从性",
      "fontesBibliograficas": "中国药典、UpToDate、Micromedex、BNF"
    }
  }
}