{
  "PT": {
    "external": {
      "name": "Óleo de Borragem",
      "suspension": "Suspender 5 dias antes de procedimentos com risco de sangramento",
      "risk": "Risco leve de sangramento por efeito antiagregante; pode causar desconforto gastrointestinal leve",
      "reintroduction": "Reintroduzir após 48–72h, se hemostasia estiver controlada"
    },
    "bulario": {
      "nomePrincipioAtivo": "Borago officinalis (óleo extraído das sementes)",
      "nomeComercial": "Boraprim, GLA Borragem, Oenobiol, Borage Oil",
      "mecanismoAcao": "Fonte rica em ácido gama-linolênico (GLA), precursor de prostaglandinas anti-inflamatórias da série 1 (PGE1)",
      "farmacocinetica": "Absorção intestinal lenta, metabolizado no fígado em prostanoides; ação em 7–14 dias",
      "farmacodinamica": "Regula inflamação, melhora hidratação cutânea e reduz dor articular e sintomas pré-menstruais",
      "indicacoes": "Dermatite atópica, artrite reumatoide leve, TPM, mastalgia, síndrome da menopausa",
      "reacoesAdversas": "Náusea, diarreia, eructações, flatulência, cefaleia leve",
      "riscoGravidez": "Categoria C – evitar pelo potencial de estímulo uterino",
      "riscoLactacao": "Evitar uso por falta de dados de segurança",
      "administracao": "Oral",
      "doseMaxima": "1500 mg/dia (fornecendo até 300 mg de GLA)",
      "doseMinima": "500 mg/dia",
      "classificacao": "Fitoterápico anti-inflamatório e modulador hormonal suave",
      "apresentacao": "Cápsulas oleosas de 500 a 1000 mg",
      "interacaoMedicamento": "Potencializa anticoagulantes e AINEs; evitar uso com fenotiazinas",
      "posologia": "500–1000 mg 1 a 2 vezes ao dia",
      "armazenamento": "Armazenar em local fresco, protegido da luz e umidade",
      "preparo": "Óleo prensado a frio, sem solventes; teor mínimo de 20% GLA",
      "solucoesCompatíveis": "Associado a óleo de prímula, vitamina E, ômega-3",
      "contraindicacoes": "Epilepsia, uso de fenotiazinas, distúrbios hemorrágicos, gravidez",
      "cuidadosMedicos": "Monitorar uso concomitante com anticoagulantes",
      "cuidadosFarmaceuticos": "Verificar teor de GLA e origem (prensagem a frio)",
      "cuidadosEnfermagem": "Observar efeitos digestivos e melhora clínica",
      "fontesBibliograficas": "ANVISA, Natural Medicines, EMA, Medscape, UpToDate"
    }
  },
  "US": {
    "external": {
      "name": "Borage Oil",
      "suspension": "Discontinue 5 days before procedures with bleeding risk",
      "risk": "May increase bleeding tendency; mild GI side effects possible",
      "reintroduction": "Restart 48–72h after procedure if bleeding is controlled"
    },
    "bulario": {
      "nomePrincipioAtivo": "Borago officinalis (seed oil)",
      "nomeComercial": "Borage Oil, Nature’s Way Borage, GLA Complex, Puritan's Pride",
      "mecanismoAcao": "High in gamma-linolenic acid (GLA), which converts to anti-inflammatory prostaglandins (PGE1)",
      "farmacocinetica": "Slow intestinal absorption, hepatic conversion; onset in 1–2 weeks",
      "farmacodinamica": "Anti-inflammatory, improves skin barrier, reduces PMS and joint symptoms",
      "indicacoes": "Eczema, mild rheumatoid arthritis, PMS, mastalgia, menopausal symptoms",
      "reacoesAdversas": "GI upset, burping, flatulence, mild headache",
      "riscoGravidez": "Category C – avoid due to uterine stimulation risk",
      "riscoLactacao": "Avoid during breastfeeding; insufficient safety data",
      "administracao": "Oral",
      "doseMaxima": "1500 mg/day (up to 300 mg GLA)",
      "doseMinima": "500 mg/day",
      "classificacao": "Herbal anti-inflammatory and hormonal modulator",
      "apresentacao": "Softgel capsules (500–1000 mg)",
      "interacaoMedicamento": "May potentiate anticoagulants and NSAIDs; avoid with phenothiazines",
      "posologia": "500–1000 mg 1–2x daily",
      "armazenamento": "Store in a cool, dry place away from light",
      "preparo": "Cold-pressed oil with ≥20% GLA content",
      "solucoesCompatíveis": "Formulas with evening primrose, vitamin E, omega-3",
      "contraindicacoes": "Seizure disorders, phenothiazine use, pregnancy, bleeding disorders",
      "cuidadosMedicos": "Monitor anticoagulant co-use",
      "cuidadosFarmaceuticos": "Check GLA content and cold-press origin",
      "cuidadosEnfermagem": "Monitor GI tolerance and therapeutic response",
      "fontesBibliograficas": "NIH, Natural Medicines, Medscape, EMA, UpToDate"
    }
  },
  "ES": {
    "external": {
      "name": "Aceite de Borraja",
      "suspension": "Suspender 5 días antes de procedimientos con riesgo hemorrágico",
      "risk": "Riesgo leve de sangrado; puede causar molestias digestivas",
      "reintroduction": "Reanudar 48–72h después si no hay sangrado"
    },
    "bulario": {
      "nomePrincipioAtivo": "Borago officinalis (aceite de semillas)",
      "nomeComercial": "Borage Oil, GLA Complex, Aceite de Borraja Eladiet",
      "mecanismoAcao": "Rico en GLA, precursor de prostaglandinas antiinflamatorias (PGE1)",
      "farmacocinetica": "Absorción lenta, metabolización hepática; efecto en 7–14 días",
      "farmacodinamica": "Antiinflamatorio, mejora la piel, reduce síntomas de TPM y artritis",
      "indicacoes": "Dermatitis atópica, artritis leve, síndrome premenstrual, mastalgia",
      "reacoesAdversas": "Náuseas, gases, eructos, cefalea leve",
      "riscoGravidez": "Categoría C – evitar por riesgo uterotónico",
      "riscoLactacao": "No se recomienda por falta de datos",
      "administracao": "Oral",
      "doseMaxima": "1500 mg/día (hasta 300 mg de GLA)",
      "doseMinima": "500 mg/día",
      "classificacao": "Fitoterápico antiinflamatorio y regulador hormonal",
      "apresentacao": "Cápsulas blandas (500–1000 mg)",
      "interacaoMedicamento": "Potencia AINEs, anticoagulantes; evitar con fenotiazinas",
      "posologia": "500–1000 mg 1–2 veces/día",
      "armazenamento": "Lugar seco, fresco y sin luz",
      "preparo": "Aceite prensado en frío con ≥20% de GLA",
      "solucoesCompatíveis": "Combinado con onagra, vitamina E, omega-3",
      "contraindicacoes": "Epilepsia, embarazo, trastornos hemorrágicos",
      "cuidadosMedicos": "Vigilar si se usa con anticoagulantes",
      "cuidadosFarmaceuticos": "Verificar prensado en frío y % de GLA",
      "cuidadosEnfermagem": "Observar tolerancia digestiva y respuesta clínica",
      "fontesBibliograficas": "EMA, ESCOP, Natural Medicines, Medscape"
    }
  },
  "CH": {
    "external": {
      "name": "琉璃苣油（Borage Oil）",
      "suspension": "术前5天停用，尤其有出血风险者",
      "risk": "可能轻度抑制血小板聚集，轻度胃肠不适",
      "reintroduction": "术后48–72小时在无出血下可重新使用"
    },
    "bulario": {
      "nomePrincipioAtivo": "琉璃苣籽油（Borago officinalis）",
      "nomeComercial": "琉璃苣胶囊、GLA植物油、皮肤康软胶囊",
      "mecanismoAcao": "富含GLA，转化为PGE1抗炎前列腺素，调节激素和免疫",
      "farmacocinetica": "肠道缓慢吸收，肝脏代谢，作用起效约1–2周",
      "farmacodinamica": "抗炎，改善皮肤干燥与湿疹，缓解关节痛与经前症状",
      "indicacoes": "湿疹、类风湿关节炎、经前综合征、乳房胀痛、绝经期症状",
      "reacoesAdversas": "恶心、腹胀、打嗝、轻度头痛",
      "riscoGravidez": "C类 – 孕期禁用（可能刺激子宫）",
      "riscoLactacao": "不推荐哺乳期使用",
      "administracao": "口服",
      "doseMaxima": "每日不超过1500毫克（含GLA至300毫克）",
      "doseMinima": "每日500毫克",
      "classificacao": "植物性抗炎剂、激素调节营养素",
      "apresentacao": "软胶囊（500–1000毫克）",
      "interacaoMedicamento": "增强NSAIDs、抗凝药物作用，禁与吩噻嗪类合用",
      "posologia": "每日1–2次，每次500–1000毫克",
      "armazenamento": "阴凉干燥避光保存",
      "preparo": "冷榨提取，含GLA≥20%",
      "solucoesCompatíveis": "可与月见草油、维E、鱼油配合使用",
      "contraindicacoes": "癫痫、孕期、凝血障碍、吩噻嗪用药者禁用",
      "cuidadosMedicos": "与抗凝药物合用需评估出血风险",
      "cuidadosFarmaceuticos": "核实GLA含量和冷榨来源",
      "cuidadosEnfermagem": "观察胃肠反应及临床改善",
      "fontesBibliograficas": "中国药典、Natural Medicines、EMA、UpToDate、Medscape"
    }
  }
}