{
  "PT": {
    "external": {
      "name": "Vitamina A",
      "suspension": "Não é necessário suspender antes de cirurgias de rotina",
      "risk": "Altas doses podem causar hepatotoxicidade e hipertensão intracraniana; precaução em cirurgias com risco hepático ou hipertensão intracraniana",
      "reintroduction": "Manter ou reiniciar no pós-operatório se houver deficiência comprovada; evitar megadoses sem justificativa clínica"
    },
    "bulario": {
      "nomePrincipioAtivo": "Palmitato de retinol / Retinol",
      "nomeComercial": "Arovit, AD-Til, Aderogil A, Multigripe A+",
      "mecanismoAcao": "Essencial para diferenciação celular, imunidade, função visual (rodopsina), integridade epitelial e metabolismo ósseo",
      "farmacocinetica": "Absorção intestinal com lipídios; armazenada no fígado; excreção biliar e renal",
      "farmacodinamica": "Regula expressão gênica, imunidade inata e adaptativa, crescimento e integridade da pele e mucosas",
      "indicacoes": "Deficiência nutricional, xeroftalmia, imunodeficiência, sarampo, acne grave (uso dermatológico)",
      "reacoesAdversas": "Hepatotoxicidade, náusea, cefaleia, descamação cutânea, visão borrada, pseudotumor cerebral",
      "riscoGravidez": "Categoria X em megadoses – teratogênico acima de 10.000 UI/dia",
      "riscoLactacao": "Seguro em doses fisiológicas; evitar megadoses",
      "administracao": "Oral ou intramuscular",
      "doseMaxima": "10.000 UI/dia (segura); até 50.000–100.000 UI/dia em deficiências graves (curta duração)",
      "doseMinima": "600–900 mcg RAE/dia (≈2.000–3.000 UI/dia)",
      "classificacao": "Vitamina lipossolúvel essencial",
      "apresentacao": "Cápsulas gelatinosas, solução oral, gotas, injetável IM",
      "interacaoMedicamento": "Interage com orlistate, anticoncepcionais, isotretinoína; álcool potencializa toxicidade hepática",
      "posologia": "5.000–10.000 UI/dia em suplementação; até 200.000 UI dose única em xeroftalmia",
      "armazenamento": "Temperatura ambiente, protegido da luz e umidade",
      "preparo": "Agitar frascos líquidos antes do uso",
      "solucoesCompatíveis": "Soro fisiológico para IM; não IV",
      "contraindicacoes": "Gravidez (megadoses), hipervitaminose A, hepatopatias graves",
      "cuidadosMedicos": "Avaliar risco/benefício em mulheres férteis; monitorar função hepática em uso prolongado",
      "cuidadosFarmaceuticos": "Evitar superdosagem; respeitar RDA e forma farmacêutica",
      "cuidadosEnfermagem": "Observar sinais de toxicidade e adesão ao tratamento",
      "fontesBibliograficas": "ANVISA, FDA, Micromedex, Medscape, SBEM"
    }
  },
  "US": {
    "external": {
      "name": "Vitamin A",
      "suspension": "No need to suspend before routine surgery",
      "risk": "High doses may cause hepatotoxicity and intracranial hypertension; use caution in liver disease or neurological surgery",
      "reintroduction": "Restart post-op if clinically indicated; avoid megadoses without strong justification"
    },
    "bulario": {
      "nomePrincipioAtivo": "Retinol / Retinyl palmitate",
      "nomeComercial": "A-Retinol, Nature’s Way Vitamin A, Solgar",
      "mecanismoAcao": "Crucial for gene expression, immunity, epithelial integrity, and visual function",
      "farmacocinetica": "Fat-soluble; liver storage; eliminated via bile and urine",
      "farmacodinamica": "Supports vision, immune defense, tissue growth, and epithelial differentiation",
      "indicacoes": "Deficiency, xerophthalmia, measles, acne, immune deficiency",
      "reacoesAdversas": "Liver damage, headache, dry skin, nausea, blurred vision, pseudotumor cerebri",
      "riscoGravidez": "Category X in megadoses – teratogenic over 10,000 IU/day",
      "riscoLactacao": "Safe in physiological doses; avoid high doses",
      "administracao": "Oral or intramuscular",
      "doseMaxima": "10,000 IU/day; up to 100,000 IU/day short term for deficiency",
      "doseMinima": "600–900 mcg RAE/day (~2,000–3,000 IU)",
      "classificacao": "Essential fat-soluble vitamin",
      "apresentacao": "Softgel capsules, oral drops, IM injection",
      "interacaoMedicamento": "Interactions with orlistat, contraceptives, retinoids; alcohol enhances liver toxicity",
      "posologia": "5,000–10,000 IU/day typical; 200,000 IU single dose for severe deficiency",
      "armazenamento": "Room temp, protect from light and humidity",
      "preparo": "Shake liquids before use",
      "solucoesCompatíveis": "0.9% saline for IM; not for IV",
      "contraindicacoes": "Pregnancy (megadoses), hypervitaminosis A, severe liver disease",
      "cuidadosMedicos": "Avoid excess in women of childbearing age; monitor liver function",
      "cuidadosFarmaceuticos": "Warn about overdose risk and supplement source",
      "cuidadosEnfermagem": "Monitor for toxicity and compliance",
      "fontesBibliograficas": "FDA, Medscape, Micromedex, NIH"
    }
  },
  "ES": {
    "external": {
      "name": "Vitamina A",
      "suspension": "No requiere suspensión antes de cirugía habitual",
      "risk": "Dosis altas pueden causar hepatotoxicidad e hipertensión intracraneal; precaución en hepatopatías",
      "reintroduction": "Reanudar si hay déficit documentado; evitar sobredosis"
    },
    "bulario": {
      "nomePrincipioAtivo": "Palmitato de retinol",
      "nomeComercial": "Retinol Forte, Arovit, Vitamina A GSN",
      "mecanismoAcao": "Cofactor para funciones visuales, inmunitarias, epiteliales y crecimiento celular",
      "farmacocinetica": "Lipofílica, acumulación hepática, excreción biliar y renal",
      "farmacodinamica": "Favorece diferenciación celular, inmunidad y visión",
      "indicacoes": "Deficiencia nutricional, xeroftalmía, sarampión, acné",
      "reacoesAdversas": "Hepatotoxicidad, náuseas, sequedad cutánea, hipertensión endocraneana",
      "riscoGravidez": "Categoría X en megadosis – teratogénica",
      "riscoLactacao": "Segura en dosis fisiológicas",
      "administracao": "Oral o intramuscular",
      "doseMaxima": "10.000 UI/día; hasta 100.000 UI en terapia breve",
      "doseMinima": "600–900 mcg RAE/día",
      "classificacao": "Vitamina liposoluble esencial",
      "apresentacao": "Cápsulas, solución oral, ampollas IM",
      "interacaoMedicamento": "Orlistat, isotretinoína, anticonceptivos, alcohol",
      "posologia": "5.000–10.000 UI/día; 200.000 UI dosis única en xeroftalmía",
      "armazenamento": "15–30°C, protegido de luz y humedad",
      "preparo": "Agitar líquidos antes de uso",
      "solucoesCompatíveis": "ClNa 0,9% (IM)",
      "contraindicacoes": "Hipervitaminosis A, embarazo (megadosis)",
      "cuidadosMedicos": "Control hepático y evitar sobredosis en embarazadas",
      "cuidadosFarmaceuticos": "Evitar administración prolongada sin seguimiento",
      "cuidadosEnfermagem": "Observar toxicidad hepática o neurológica",
      "fontesBibliograficas": "EMA, Micromedex, Medscape"
    }
  },
  "CH": {
    "external": {
      "name": "维生素A",
      "suspension": "常规手术前无需停用，除非使用大剂量",
      "risk": "大剂量可能导致肝毒性和颅内高压；术中应注意肝功能和神经稳定性",
      "reintroduction": "术后可根据缺乏状态恢复使用；避免高剂量补充"
    },
    "bulario": {
      "nomePrincipioAtivo": "视黄醇/视黄酸酯",
      "nomeComercial": "维生素A胶囊、Arovit、复合维生素制剂",
      "mecanismoAcao": "调节基因表达、上皮修复、视紫红质合成和免疫功能",
      "farmacocinetica": "脂溶性，肝脏储存，经胆汁和尿液排泄",
      "farmacodinamica": "促进视觉、皮肤健康、上皮组织修复与免疫反应",
      "indicacoes": "维生素A缺乏、干眼症、麻疹、皮肤病（如痤疮）",
      "reacoesAdversas": "恶心、皮肤干燥、肝毒性、颅内压升高、视物模糊",
      "riscoGravidez": "X类 – 高剂量具致畸性",
      "riscoLactacao": "生理剂量安全",
      "administracao": "口服或肌肉注射",
      "doseMaxima": "每日10,000 IU常规；严重缺乏时可至200,000 IU短期",
      "doseMinima": "每日600–900微克RAE",
      "classificacao": "脂溶性维生素",
      "apresentacao": "胶囊、口服液、IM注射液",
      "interacaoMedicamento": "与奥利司他、异维A酸、避孕药、酒精等互相影响",
      "posologia": "5,000–10,000 IU每日或一次性补充",
      "armazenamento": "15–30°C，避光避湿",
      "preparo": "液体需摇匀",
      "solucoesCompatíveis": "0.9%氯化钠（仅限肌注）",
      "contraindicacoes": "高剂量时孕妇禁用、肝病、维生素A过量",
      "cuidadosMedicos": "监测肝功能、妊娠状态",
      "cuidadosFarmaceuticos": "强调安全剂量与孕妇禁用",
      "cuidadosEnfermagem": "观察毒性表现和依从性",
      "fontesBibliograficas": "中国药典、FDA、EMA、Micromedex"
    }
  }
}